doan/__init__.py
doan/dataset.py
doan/graph.py
doan/stat.py
doan/util.py
doan/tests/__init__.py
doan/tests/test_all.py
doan-0.2.3.dist-info/DESCRIPTION.rst
doan-0.2.3.dist-info/METADATA
doan-0.2.3.dist-info/RECORD
doan-0.2.3.dist-info/WHEEL
doan-0.2.3.dist-info/metadata.json
doan-0.2.3.dist-info/top_level.txt
