Metadata-Version: 2.0
Name: doan
Version: 0.2.3
Summary: Simple library for analytics
Home-page: https://github.com/amadev/doan
Author: Andrey Volkov
Author-email: amadev@mail.ru
License: MIT
Keywords: analytics statistics
Platform: UNKNOWN
Classifier: Development Status :: 3 - Alpha
Classifier: Environment :: Console
Classifier: Intended Audience :: Developers
Classifier: Intended Audience :: System Administrators
Classifier: License :: OSI Approved :: MIT License
Classifier: Operating System :: POSIX :: Linux
Classifier: Programming Language :: Python :: 3
Classifier: Topic :: Utilities
Classifier: Topic :: Scientific/Engineering :: Information Analysis
Requires-Dist: matplotlib (>=1.5.1)
